{
  "job_title": "Business Systems Analyst",
  "company": "Bristol Myers Squibb",
  "location": "Summit, NJ",
  "job_url": "https://www.linkedin.com/jobs/view/4412900582",
  "ats_keywords": [
    "SAP S4/Hana",
    "EWM",
    "system implementation",
    "SDLC",
    "training",
    "test scripts",
    "SOP",
    "work instructions",
    "manufacturing",
    "quality",
    "procurement",
    "warehouse",
    "MM",
    "QM",
    "IM",
    "MDG",
    "troubleshooting",
    "change management",
    "user acceptance testing",
    "vendor management",
    "data modeling",
    "analytics",
    "Microsoft Windows",
    "customer service",
    "life science"
  ],
  "score": 28,
  "matched_keywords": [
    "system implementation",
    "training",
    "test scripts",
    "SOP",
    "work instructions",
    "SDLC",
    "troubleshooting",
    "data modeling",
    "analytics",
    "Microsoft Windows"
  ],
  "missing_keywords": [
    "SAP S4/Hana",
    "EWM",
    "manufacturing",
    "quality",
    "procurement",
    "warehouse",
    "MM",
    "QM",
    "IM",
    "MDG",
    "change management",
    "user acceptance testing",
    "vendor management",
    "customer service",
    "life science"
  ],
  "strengths": [
    "strong analytics and data modeling",
    "experience automating reports (Python, ETL)",
    "developed test/workflow automations",
    "created documentation and governance",
    "SQL and database optimization"
  ],
  "weaknesses": [
    "no SAP S4/Hana or EWM experience listed",
    "no manufacturing or life\u2011science domain experience",
    "limited SAP module knowledge (MM/QM/IM/MDG absent)",
    "no explicit UAT or SAP change management experience",
    "no vendor/third\u2011party SAP support experience"
  ],
  "improvement_bullets": [],
  "cover_letter": ""
}