{
  "job_title": "Senior Administrative Support Assistant",
  "company": "Northwell Health",
  "location": "Sleepy Hollow, NY",
  "job_url": "https://www.linkedin.com/jobs/view/4430701349",
  "ats_keywords": [
    "Microsoft Office",
    "Typing",
    "Scheduling",
    "Record keeping",
    "Customer service",
    "Answering telephones",
    "Meeting minutes",
    "Inventory management",
    "Ordering supplies",
    "Payment collection",
    "Filing",
    "Data entry",
    "Reporting",
    "SOP documentation",
    "Onboarding",
    "Excel",
    "Communication",
    "JIRA",
    "Confluence",
    "SQL",
    "Power BI",
    "Automation",
    "Workflow optimization",
    "Project documentation",
    "Team coordination"
  ],
  "score": 62,
  "matched_keywords": [
    "Microsoft Office",
    "Typing",
    "Scheduling",
    "Record keeping",
    "Meeting minutes",
    "Filing",
    "Reporting",
    "SOP documentation",
    "Onboarding",
    "Excel",
    "Communication",
    "Automation",
    "Workflow optimization",
    "Team coordination",
    "Payment collection"
  ],
  "missing_keywords": [
    "Answering telephones",
    "Inventory management",
    "Ordering supplies",
    "Customer service",
    "Data entry",
    "JIRA",
    "Confluence",
    "Power BI",
    "SQL",
    "Project documentation"
  ],
  "strengths": [
    "Strong technical reporting (Power BI, Excel)",
    "Process automation and workflow improvement",
    "Documented SOPs and onboarding reduction",
    "Quantified operational impact",
    "Cross-functional coordination"
  ],
  "weaknesses": [
    "Limited explicit clerical/front-desk experience",
    "No explicit phone/visitor handling details",
    "Inventory/supply management not shown",
    "Payment collection experience not detailed",
    "Only 3 years relevant ops/clerical overlap"
  ],
  "improvement_bullets": [],
  "cover_letter": ""
}