{
  "job_title": "Founding Engineer, Roivant Health",
  "company": "Roivant",
  "location": "New York, NY",
  "job_url": "https://www.linkedin.com/jobs/view/4340165971",
  "ats_keywords": [
    "Python",
    "ML/AI systems",
    "ETL pipelines",
    "data pipelines",
    "SQL",
    "PostgreSQL",
    "BigQuery",
    "Snowflake",
    "AWS S3",
    "data engineering",
    "model training",
    "model inference",
    "multimodal data",
    "production deployment",
    "version control (Git)",
    "APIs",
    "data visualization",
    "Power BI",
    "Tableau",
    "automation",
    "JIRA",
    "Confluence",
    "testable codebases",
    "scalable systems",
    "cross-functional collaboration"
  ],
  "score": 62,
  "matched_keywords": [
    "Python",
    "ETL pipelines",
    "SQL",
    "PostgreSQL",
    "BigQuery",
    "Snowflake",
    "AWS S3",
    "data engineering",
    "version control (Git)",
    "APIs",
    "Power BI",
    "Tableau",
    "automation",
    "JIRA",
    "Confluence",
    "cross-functional collaboration",
    "data pipelines",
    "data visualization"
  ],
  "missing_keywords": [
    "ML/AI systems",
    "model training",
    "model inference",
    "multimodal data",
    "production deployment",
    "testable codebases",
    "scalable systems",
    "Python engineering",
    "omics",
    "imaging",
    "sensor data",
    "clinical text",
    "healthcare data",
    "clinical/domain expertise"
  ],
  "strengths": [
    "Strong Python and SQL experience",
    "Hands-on ETL and data pipeline development",
    "Experience with cloud data platforms (BigQuery, Snowflake, S3)",
    "Delivered quantified operational impact (time savings, acquisition gains)",
    "Cross-functional collaboration and documentation skills"
  ],
  "weaknesses": [
    "Limited demonstrated ML/AI production deployment",
    "No explicit multimodal health data experience",
    "No quantified model training or inference work",
    "Lacks explicit clinical or biomedical domain experience",
    "Limited years in senior engineering roles"
  ],
  "improvement_bullets": [],
  "cover_letter": ""
}