{
  "job_title": "Analyst/ Associate: Equity Research, Internet",
  "company": "Bank of America",
  "location": "New York, NY",
  "job_url": "https://www.linkedin.com/jobs/view/4416257856",
  "ats_keywords": [
    "financial modeling",
    "valuation",
    "Excel",
    "Advanced Excel",
    "PowerPoint",
    "data visualization",
    "industry research",
    "quantitative analysis",
    "SQL",
    "Python",
    "time-sensitive reporting",
    "market research",
    "report writing",
    "data analysis",
    "ETL",
    "Dashboards",
    "Power BI",
    "Tableau",
    "financial statements",
    "communication",
    "team collaboration",
    "attention to detail",
    "client inquiries",
    "VBA",
    "CFA progress"
  ],
  "score": 58,
  "matched_keywords": [
    "Excel",
    "Advanced Excel",
    "PowerPoint",
    "data visualization",
    "report writing",
    "data analysis",
    "SQL",
    "Python",
    "Power BI",
    "Tableau",
    "ETL",
    "Dashboards",
    "time-sensitive reporting",
    "team collaboration",
    "attention to detail",
    "communication"
  ],
  "missing_keywords": [
    "financial modeling",
    "valuation",
    "industry research",
    "quantitative analysis",
    "market research",
    "financial statements",
    "VBA",
    "CFA progress",
    "client inquiries",
    "interview industry experts"
  ],
  "strengths": [
    "Strong data tooling (SQL, Python, Power BI, Tableau)",
    "Advanced Excel and dashboard creation",
    "ETL and data modeling experience",
    "Proven process improvements with measurable impact",
    "Cross-functional collaboration"
  ],
  "weaknesses": [
    "Limited direct finance/accounting or financial modeling experience",
    "No explicit valuation or income/balance/cash flow modeling",
    "Under a year of formal research/IB/VC experience",
    "No VBA or documented pursuit of CFA",
    "Limited evidence of industry/company coverage or client-facing research"
  ],
  "improvement_bullets": [],
  "cover_letter": ""
}