{
  "job_title": "Production Engineering",
  "company": "Meta",
  "location": "New York, NY",
  "job_url": "https://www.linkedin.com/jobs/view/4403755486",
  "ats_keywords": [
    "Linux",
    "MySQL",
    "Python",
    "PostgreSQL",
    "Kubernetes",
    "Terraform",
    "Networking",
    "Capacity planning",
    "Load Balancing",
    "CDN",
    "Java",
    "Go",
    "C++",
    "Cloud (AWS S3)",
    "ETL",
    "SQL",
    "Git",
    "APIs",
    "On-call",
    "Production systems",
    "Performance debugging",
    "Automation",
    "AI tools",
    "Documentation",
    "Scaling"
  ],
  "score": 32,
  "matched_keywords": [
    "MySQL",
    "Python",
    "PostgreSQL",
    "SQL",
    "Git",
    "APIs",
    "Cloud (AWS S3)",
    "ETL",
    "Automation",
    "Documentation",
    "AI tools"
  ],
  "missing_keywords": [
    "Linux",
    "Kubernetes",
    "Terraform",
    "Networking",
    "Capacity planning",
    "Load Balancing",
    "CDN",
    "Java",
    "Go",
    "C++",
    "On-call",
    "Production systems",
    "Performance debugging",
    "Scaling"
  ],
  "strengths": [
    "Strong SQL and database modeling",
    "Python ETL and analytics pipelines",
    "Data visualization and reporting (Power BI, Tableau)",
    "Documented SOPs and project documentation",
    "Experience integrating APIs and cross-team collaboration"
  ],
  "weaknesses": [
    "Limited infra/sysadmin (Linux/UNIX) evidence",
    "No Kubernetes/Terraform or infra-as-code experience",
    "Lacks demonstrated production on-call or incident response",
    "Insufficient systems programming language experience (Java/Go/C++)",
    "Limited explicit capacity planning or networking experience"
  ],
  "improvement_bullets": [],
  "cover_letter": ""
}