{
  "job_title": "Data Engineer",
  "company": "Realtek Consulting LLC",
  "location": "Jersey City, NJ",
  "job_url": "https://www.linkedin.com/jobs/view/4416576541",
  "ats_keywords": [
    "Python",
    "PySpark",
    "Spark",
    "Scala",
    "Snowflake",
    "Databricks",
    "Delta tables",
    "Apache Iceberg",
    "data pipelines",
    "performance tuning",
    "cost optimization",
    "scaling strategies",
    "ETL/ELT",
    "dbt",
    "Airflow",
    "BigQuery",
    "GCS",
    "data modeling",
    "SQL",
    "CI/CD",
    "data quality",
    "Great Expectations",
    "Docker",
    "Postgres",
    "Power BI",
    "Tableau"
  ],
  "score": 58,
  "matched_keywords": [
    "Python",
    "Snowflake",
    "data pipelines",
    "ETL/ELT",
    "dbt",
    "Airflow",
    "BigQuery",
    "GCS",
    "data modeling",
    "SQL",
    "CI/CD",
    "data quality",
    "Great Expectations",
    "Docker",
    "Postgres",
    "Power BI",
    "Tableau",
    "performance tuning",
    "cost optimization",
    "scaling strategies"
  ],
  "missing_keywords": [
    "PySpark",
    "Spark",
    "Scala",
    "Databricks",
    "Delta tables",
    "Apache Iceberg",
    "partitioning/compaction",
    "ACID/time travel",
    "schema evolution"
  ],
  "strengths": [
    "Strong Python and SQL experience",
    "Hands-on ETL/ELT and Airflow pipelines",
    "dbt modeling and data quality with Great Expectations",
    "Cloud experience (BigQuery, GCS, Snowflake)",
    "Quantified impact in prior roles"
  ],
  "weaknesses": [
    "No PySpark/Spark/Scala experience listed",
    "No Databricks hands-on experience",
    "No explicit Delta table or Iceberg experience",
    "Limited enterprise-scale pipeline examples",
    "Less than required 12+ years experience"
  ],
  "improvement_bullets": [],
  "cover_letter": ""
}