{
  "job_title": "Senior Data Analyst with P&C insurance Exp  Woodbridge NJ",
  "company": "ReignMarkconsultingservices",
  "location": "Woodbridge, NJ",
  "job_url": "https://www.linkedin.com/jobs/view/4413064032",
  "ats_keywords": [
    "SQL",
    "data mapping",
    "data transformation",
    "SDLC",
    "testing",
    "ETL",
    "Python",
    "cloud",
    "Snowflake",
    "BigQuery",
    "Power BI",
    "Tableau",
    "Advanced Excel",
    "reporting",
    "relational databases",
    "data governance",
    "communication",
    "stakeholder collaboration",
    "query optimization",
    "DB2",
    "compliance reporting",
    "P&C Insurance",
    "supervisory experience",
    "AWS",
    "Git"
  ],
  "score": 68,
  "matched_keywords": [
    "SQL",
    "data transformation",
    "SDLC",
    "testing",
    "ETL",
    "Python",
    "cloud",
    "Snowflake",
    "BigQuery",
    "Power BI",
    "Tableau",
    "Advanced Excel",
    "reporting",
    "relational databases",
    "data governance",
    "communication",
    "stakeholder collaboration",
    "query optimization",
    "AWS",
    "Git"
  ],
  "missing_keywords": [
    "data mapping",
    "DB2",
    "compliance reporting",
    "P&C Insurance",
    "supervisory experience"
  ],
  "strengths": [
    "Strong SQL and query optimization",
    "Hands-on ETL and pipeline development",
    "Proven reporting and visualization (Power BI/Tableau)",
    "Cloud data platform experience (Snowflake/BigQuery/AWS)",
    "Effective stakeholder communication"
  ],
  "weaknesses": [
    "No P&C insurance domain experience",
    "No DB2 exposure listed",
    "No explicit compliance/statutory reporting experience",
    "Limited years of experience (\u22483 years post-2023 roles)",
    "No documented supervisory/team lead title"
  ],
  "improvement_bullets": [],
  "cover_letter": ""
}