{
  "job_title": "Director of Workflow Engineering",
  "company": "Thomson Reuters",
  "location": "New York, NY",
  "job_url": "https://www.linkedin.com/jobs/view/4414462985",
  "ats_keywords": [
    "ServiceNow",
    "workflow",
    "automation",
    "integrations",
    "APIs",
    "orchestration",
    "CI/CD",
    "cloud",
    "monitoring",
    "platform governance",
    "SDLC",
    "release management",
    "AI",
    "Predictive Intelligence",
    "NowAssist",
    "CMDB",
    "event-driven",
    "telemetry",
    "auditability",
    "risk management",
    "leadership",
    "stakeholder management",
    "SQL",
    "Python",
    "CI/CD pipeline"
  ],
  "score": 28,
  "matched_keywords": [
    "automation",
    "integrations",
    "APIs",
    "CI/CD",
    "cloud",
    "monitoring",
    "SQL",
    "Python",
    "Git",
    "platform governance",
    "release management",
    "data governance",
    "telemetry",
    "orchestration",
    "stakeholder management",
    "leadership"
  ],
  "missing_keywords": [
    "ServiceNow",
    "workflow",
    "Predictive Intelligence",
    "NowAssist",
    "CMDB",
    "event-driven",
    "auditability",
    "risk management",
    "agentic automations",
    "operational safety",
    "ITSM",
    "ServiceNow certifications",
    "ITIL",
    "cloud platforms (AWS, Azure)",
    "platform roadmap",
    "real-time execution",
    "global operations",
    "operational runbooks"
  ],
  "strengths": [
    "Python and SQL proficiency",
    "CI/CD and Git experience",
    "Data governance and reporting",
    "Automation reducing manual toil",
    "Stakeholder communication"
  ],
  "weaknesses": [
    "No ServiceNow experience listed",
    "Limited ITSM/Service management background",
    "No ServiceNow or ITIL certifications",
    "Lacks explicit CMDB/integration with monitoring tools",
    "Limited senior leadership/platform roadmap evidence"
  ],
  "improvement_bullets": [],
  "cover_letter": ""
}