{
  "job_title": "Analytics Developer - Alteryx & BO",
  "company": "Tata Consultancy Services",
  "location": "Mountain Lakes, NJ",
  "job_url": "https://www.linkedin.com/jobs/view/4406906535",
  "ats_keywords": [
    "Alteryx",
    "SQL",
    "Snowflake",
    "SAP HANA",
    "Tableau",
    "Power BI",
    "Python",
    "R",
    "ETL",
    "data pipelines",
    "data modeling",
    "visualization",
    "performance tuning",
    "automation",
    "data engineering",
    "stored procedures",
    "cloud",
    "BigQuery",
    "Git",
    "version control",
    "KPIs",
    "manufacturing",
    "supply chain",
    "certification",
    "leadership"
  ],
  "score": 46,
  "matched_keywords": [
    "SQL",
    "Snowflake",
    "Tableau",
    "Power BI",
    "Python",
    "R",
    "ETL",
    "data pipelines",
    "data modeling",
    "visualization",
    "automation",
    "cloud",
    "Git",
    "version control",
    "KPIs"
  ],
  "missing_keywords": [
    "Alteryx",
    "SAP HANA",
    "stored procedures",
    "performance tuning",
    "manufacturing",
    "supply chain",
    "certification",
    "leadership",
    "AS9100",
    "ITAR"
  ],
  "strengths": [
    "Strong SQL and relational query experience",
    "Hands-on Tableau and Power BI dashboarding",
    "Python-based ETL and pipeline development",
    "Snowflake cloud experience",
    "Quantified impact on process efficiency"
  ],
  "weaknesses": [
    "No Alteryx certification or experience listed",
    "No SAP HANA or stored procedure evidence",
    "Limited manufacturing/aerospace domain experience",
    "Under 12 years of relevant experience",
    "Leadership/mentoring at senior level not demonstrated"
  ],
  "improvement_bullets": [],
  "cover_letter": ""
}