{
  "job_title": "Data Engineer",
  "company": "Saragossa",
  "location": "",
  "job_url": "https://www.linkedin.com/jobs/view/4414331016",
  "ats_keywords": [
    "BigQuery",
    "dbt",
    "Airflow",
    "Python",
    "SQL",
    "ELT/ETL",
    "GCS",
    "Great Expectations",
    "CI/CD",
    "GitHub Actions",
    "Snowflake",
    "Postgres",
    "Docker",
    "Dimensional modeling",
    "data quality",
    "data pipeline",
    "data engineering",
    "Power BI",
    "Tableau",
    "private markets",
    "private equity",
    "private credit",
    "cloud",
    "data modeling",
    "automation",
    "data transformation"
  ],
  "score": 74,
  "matched_keywords": [
    "BigQuery",
    "dbt",
    "Airflow",
    "Python",
    "SQL",
    "ELT/ETL",
    "GCS",
    "Great Expectations",
    "CI/CD",
    "GitHub Actions",
    "Snowflake",
    "Postgres",
    "Docker",
    "Dimensional modeling",
    "data quality",
    "data pipeline",
    "data engineering",
    "Power BI",
    "Tableau",
    "cloud",
    "data modeling",
    "automation",
    "data transformation",
    "Git"
  ],
  "missing_keywords": [
    "private markets",
    "private equity",
    "private credit",
    "AWS",
    "asset management"
  ],
  "strengths": [
    "Strong cloud data stack experience (BigQuery, GCS, dbt)",
    "Production ELT pipeline building with Airflow and Great Expectations",
    "Proficient in Python and advanced SQL",
    "CI/CD and automation via GitHub Actions",
    "Data modeling and performance optimization (partitioning/clustering)"
  ],
  "weaknesses": [
    "No explicit private markets/private equity experience",
    "Limited years in senior data engineering roles",
    "AWS mentioned but limited evidence of deep AWS infra",
    "No explicit experience with private credit data quirks",
    "No investment/asset management domain achievements quantified"
  ],
  "improvement_bullets": [],
  "cover_letter": ""
}