{
  "job_title": "Software Engineer - Trading System Developer",
  "company": "XTX Markets",
  "location": "",
  "job_url": "https://www.linkedin.com/jobs/view/4411188043",
  "ats_keywords": [
    "Kotlin",
    "C++",
    "Java",
    "Python",
    "SQL",
    "BigQuery",
    "Docker",
    "CI/CD",
    "GitHub Actions",
    "Cloud",
    "Postgres",
    "ETL/ELT",
    "dbt",
    "Airflow",
    "Data modeling",
    "Testing",
    "Low-latency systems",
    "Trading systems",
    "Risk controls",
    "ETFs",
    "Algorithms",
    "Quantitative",
    "Networking",
    "Concurrency",
    "Performance tuning",
    "Systems design"
  ],
  "score": 34,
  "matched_keywords": [
    "Python",
    "SQL",
    "BigQuery",
    "Docker",
    "CI/CD",
    "GitHub Actions",
    "Postgres",
    "ETL/ELT",
    "dbt",
    "Airflow",
    "Data modeling",
    "Testing",
    "Cloud"
  ],
  "missing_keywords": [
    "Kotlin",
    "C++",
    "Java",
    "Low-latency systems",
    "Trading systems",
    "Risk controls",
    "ETFs",
    "Algorithms",
    "Quantitative",
    "Networking",
    "Concurrency",
    "Performance tuning",
    "Systems design"
  ],
  "strengths": [
    "Strong Python and SQL proficiency",
    "Experience with BigQuery and cloud data infra",
    "ETL/ELT pipeline design with Airflow and dbt",
    "CI/CD and Docker deployment experience",
    "Quantifiable impact in past roles"
  ],
  "weaknesses": [
    "No Kotlin or C++ experience listed",
    "No explicit low-latency or high-throughput systems experience",
    "No trading or finance-specific system work (limited ETF knowledge)",
    "Title misalignment for senior trading developer role",
    "Relatively limited years of relevant systems engineering experience"
  ],
  "improvement_bullets": [],
  "cover_letter": ""
}